dirforge/__init__.py
dirforge/core.py
dirforge-0.1.0.dist-info/METADATA
dirforge-0.1.0.dist-info/WHEEL
dirforge-0.1.0.dist-info/entry_points.txt
dirforge-0.1.0.dist-info/licenses/LICENSE
dirforge-0.1.0.dist-info/RECORD
