Metadata-Version: 2.4
Name: dirforge
Version: 0.1.0
Summary: A Python library for converting tree structure text into actual files and directories
Project-URL: Homepage, https://github.com/obedienceadara/dirforge
Project-URL: Bug Tracker, https://github.com/obedienceadara/dirforge/issues
Author-email: Obedience Adara <obedienceadara@gmail.com>
License-File: LICENSE
Classifier: License :: OSI Approved :: MIT License
Classifier: Operating System :: OS Independent
Classifier: Programming Language :: Python :: 3
Classifier: Topic :: System :: Filesystems
Classifier: Topic :: Utilities
Requires-Python: >=3.7
Requires-Dist: pathlib
